[{"c":9070400,"n":"Atlantida Department,Honduras","t":"Department"},{"c":9069979,"n":"Bay Islands Department,Honduras","t":"Department"},{"c":9069983,"n":"Choluteca Department,Honduras","t":"Department"},{"c":9069974,"n":"Colon Department,Honduras","t":"Department"},{"c":9069976,"n":"Comayagua Department,Honduras","t":"Department"},{"c":9069978,"n":"Copan Department,Honduras","t":"Department"},{"c":9069970,"n":"Cortes Department,Honduras","t":"Department"},{"c":9069981,"n":"El Paraiso Department,Honduras","t":"Department"},{"c":9069972,"n":"Francisco Morazan Department,Honduras","t":"Department"},{"c":9070402,"n":"Gracias a Dios Department,Honduras","t":"Department"},{"c":2340,"n":"Honduras","t":"Country"},{"c":9069975,"n":"Intibuca Department,Honduras","t":"Department"},{"c":9069973,"n":"La Paz Department,Honduras","t":"Department"},{"c":9069977,"n":"Lempira Department,Honduras","t":"Department"},{"c":9069971,"n":"Ocotepeque Department,Honduras","t":"Department"},{"c":9069984,"n":"Olancho Department,Honduras","t":"Department"},{"c":9218708,"n":"Roatan,Bay Islands Department,Honduras","t":"Municipality"},{"c":9069980,"n":"Santa Barbara Department,Honduras","t":"Department"},{"c":9070401,"n":"Valle Department,Honduras","t":"Department"},{"c":9069982,"n":"Yoro Department,Honduras","t":"Department"}]